glowtracker/AutoFocus.py
glowtracker/Basler_control.py
glowtracker/GlowTracker.py
glowtracker/MacroScript.py
glowtracker/Microscope_macros.py
glowtracker/Zaber_control.py
glowtracker/__init__.py
glowtracker/__main__.py
glowtracker/layout.kv
glowtracker/icons/LeftButtonDisabled.jpg
glowtracker/icons/LeftButtonDisabled_Double.jpg
glowtracker/icons/LeftButtonNormal.jpg
glowtracker/icons/LeftButtonNormal_Double.jpg
glowtracker/icons/LeftButtonOnPress.jpg
glowtracker/icons/LeftButtonOnPress_Double.jpg
glowtracker/icons/RightButtonDisabled.jpg
glowtracker/icons/RightButtonDisabled_Double.jpg
glowtracker/icons/RightButtonNormal.jpg
glowtracker/icons/RightButtonNormal_Double.jpg
glowtracker/icons/RightButtonOnPress.jpg
glowtracker/icons/RightButtonOnPress_Double.jpg
glowtracker/icons/connection_off.png
glowtracker/icons/connection_on.png
glowtracker/icons/glowtracker_gray_logo.png
glowtracker/icons/play_disabled.png
glowtracker/icons/play_off.png
glowtracker/icons/play_on.png
glowtracker/icons/record_active.png
glowtracker/icons/record_inactive.jpg
glowtracker/icons/record_inactive.png
glowtracker/icons/recording-icon-png-5.png
glowtracker/icons/scholz-lab_logo.png
glowtracker/icons/snap_active.png
glowtracker/icons/snap_inactive.png
glowtracker/settings/default.pfs
glowtracker/settings/experiment_settings.json
glowtracker/settings/gui_settings.json
glowtracker-0.12.1.dist-info/licenses/LICENSE.txt
glowtracker-0.12.1.dist-info/METADATA
glowtracker-0.12.1.dist-info/WHEEL
glowtracker-0.12.1.dist-info/entry_points.txt
glowtracker-0.12.1.dist-info/top_level.txt
glowtracker-0.12.1.dist-info/RECORD
