Metadata-Version: 2.4
Name: glowtracker
Version: 0.12.1
Summary: GlowTracker provides a graphical user interface to operate a microscope. The microscope is a hardware setup designed for tracking a small animal in bright field, single or dual epi-fluorescence imaging.
Author-email: Monika Scholz <monika.scholz@mpinb.mpg.de>
Maintainer-email: Monika Scholz <monika.scholz@mpinb.mpg.de>, Takkasila Saichol <takkasila.saichol@mpinb.mpg.de>
Project-URL: Homepage, https://github.com/scholz-lab/GlowTracker
Project-URL: Issues, https://github.com/scholz-lab/GlowTracker/issues
Project-URL: Documentation, https://scholz-lab.github.io/GlowTracker/
Project-URL: Repository, https://github.com/scholz-lab/GlowTracker.git
Keywords: python,research,microscope,tracking,Zaber,Basler
Classifier: Intended Audience :: Science/Research
Classifier: Programming Language :: Python :: 3
Classifier: Topic :: Scientific/Engineering :: Bio-Informatics
Classifier: Topic :: Scientific/Engineering :: Image Recognition
Requires-Python: >=3.10
License-File: LICENSE.txt
Requires-Dist: kivy>=2.2.0
Requires-Dist: matplotlib
Requires-Dist: numpy
Requires-Dist: opencv-python
Requires-Dist: pillow
Requires-Dist: scikit-image>=0.22.0
Requires-Dist: scipy
Requires-Dist: zaber-motion
Requires-Dist: overrides
Requires-Dist: pandas
Requires-Dist: pypylon
Requires-Dist: itk-elastix
Requires-Dist: platformdirs
Requires-Dist: pyparsing
Dynamic: license-file
